credential_holder/__init__.py
credential_holder/holder.py
credential_holder/serializer.py
CredentialHolder-0.0.7.dist-info/LICENSE.txt
CredentialHolder-0.0.7.dist-info/METADATA
CredentialHolder-0.0.7.dist-info/WHEEL
CredentialHolder-0.0.7.dist-info/top_level.txt
CredentialHolder-0.0.7.dist-info/RECORD
