Metadata-Version: 2.1
Name: CredentialHolder
Version: 0.0.7
Summary: simple class for serializable and secure credential holder
Home-page: https://github.com/bmpang/PythonCredentialHolderClass
Author: brando
Author-email: snoopy20704@gmail.com
License: UNKNOWN
Platform: UNKNOWN
Classifier: Programming Language :: Python :: 3
Requires-Dist: pycryptodome
